pipictureframe/__init__.py
pipictureframe/pipictureframe.py
pipictureframe/fonts/NotoSans-Regular.ttf
pipictureframe/pi3dfuncs/__init__.py
pipictureframe/picdb/Database.py
pipictureframe/picdb/DatabaseMigrator.py
pipictureframe/picdb/DbObjects.py
pipictureframe/picdb/PictureUpdater.py
pipictureframe/picdb/__init__.py
pipictureframe/shaders/blend_new.fs
pipictureframe/shaders/blend_new.vs
pipictureframe/utils/Config.py
pipictureframe/utils/Geo.py
pipictureframe/utils/NextPictureManager.py
pipictureframe/utils/PictureReader.py
pipictureframe/utils/__init__.py
pipictureframe-0.11.3.data/scripts/pi-picture-frame
pipictureframe-0.11.3.dist-info/LICENSE
pipictureframe-0.11.3.dist-info/METADATA
pipictureframe-0.11.3.dist-info/WHEEL
pipictureframe-0.11.3.dist-info/top_level.txt
pipictureframe-0.11.3.dist-info/RECORD
