Metadata-Version: 2.1
Name: pipictureframe
Version: 0.11.3
Summary: A program to use a raspberry pi with a monitor as a digital picture frame.
Home-page: https://github.com/cornim/pipictureframe
Author: Dr. Cornelius Mund
Author-email: 
License: GPLv3
Platform: UNKNOWN
Classifier: Development Status :: 4 - Beta
Classifier: Programming Language :: Python :: 3 :: Only
Classifier: License :: OSI Approved :: GNU General Public License v3 or later (GPLv3+)
Classifier: Operating System :: POSIX :: Linux
Requires-Python: >=3.6
Requires-Dist: pi3d (>=2.41)
Requires-Dist: numpy (>=1.19.5)
Requires-Dist: Pillow (>=8.1.0)
Requires-Dist: geopy (>=2.1.0)
Requires-Dist: sqlalchemy (>=1.3.23)
Requires-Dist: python-dateutil (>=2.8.1)
